monitool.py
monitool-0.1.1.dist-info/LICENSE
monitool-0.1.1.dist-info/WHEEL
monitool-0.1.1.dist-info/METADATA
monitool-0.1.1.dist-info/RECORD
