Metadata-Version: 2.1
Name: monitool
Version: 0.1.1
Summary: A little library for writing monitoring plugins for Nagios, Icinga, and probably others that are ABI-compatible.
Author-email: Grissess <grissess@nexusg.org>
Classifier: License :: OSI Approved :: GNU General Public License v3 or later (GPLv3+)
Project-URL: Home, https://github.com/Grissess/monitool
